[
  {
    "x": 0.677419,
    "y": 2.507359,
    "theta": 10.863995
  },
  {
    "x": -0.037658,
    "y": -0.340756,
    "theta": 0.940018
  },
  {
    "x": -0.983821,
    "y": -0.363441,
    "theta": 15.485421
  },
  {
    "x": -0.220525,
    "y": 0.655149,
    "theta": 14.161132
  },
  {
    "x": 2.483413,
    "y": 1.626588,
    "theta": 2.539706
  },
  {
    "x": -1.392268,
    "y": 0.759075,
    "theta": -3.78469
  },
  {
    "x": 1.604507,
    "y": 3.42312,
    "theta": -1.951949
  },
  {
    "x": 0.976506,
    "y": -1.081415,
    "theta": -2.201578
  },
  {
    "x": -0.104059,
    "y": -1.006521,
    "theta": 9.749975
  },
  {
    "x": -0.230435,
    "y": 2.627513,
    "theta": -4.843973
  },
  {
    "x": 2.480155,
    "y": 0.40273,
    "theta": 5.236609
  },
  {
    "x": 1.950522,
    "y": -0.554463,
    "theta": 4.62447
  },
  {
    "x": -1.170865,
    "y": 1.743257,
    "theta": 7.76472
  },
  {
    "x": 0.822367,
    "y": 0.512618,
    "theta": 12.747967
  },
  {
    "x": 2.407233,
    "y": 1.515685,
    "theta": -0.601886
  }
]