[
  {
    "x": -1.039139,
    "y": 1.356106,
    "theta": 5.478046
  },
  {
    "x": 1.885933,
    "y": 0.900458,
    "theta": 2.654461
  },
  {
    "x": -0.681997,
    "y": -0.613635,
    "theta": 0.282272
  },
  {
    "x": -0.457571,
    "y": 1.91528,
    "theta": 2.335806
  },
  {
    "x": -2.399155,
    "y": 1.435769,
    "theta": 5.743893
  },
  {
    "x": -0.625086,
    "y": -1.861414,
    "theta": 5.39233
  },
  {
    "x": 2.563054,
    "y": -1.093629,
    "theta": 2.738716
  },
  {
    "x": 1.814512,
    "y": 0.765615,
    "theta": 5.79605
  },
  {
    "x": 0.925789,
    "y": 1.728757,
    "theta": 1.789045
  },
  {
    "x": 0.843319,
    "y": 0.680094,
    "theta": 2.997234
  },
  {
    "x": 0.706866,
    "y": -1.838178,
    "theta": 5.605437
  },
  {
    "x": -1.947374,
    "y": -0.293831,
    "theta": 3.860911
  },
  {
    "x": -1.757548,
    "y": -0.510512,
    "theta": 0.71927
  },
  {
    "x": 1.244845,
    "y": -1.151462,
    "theta": 2.475229
  },
  {
    "x": -1.496729,
    "y": -1.280009,
    "theta": 4.744179
  }
]