[
  {
    "x": -1.040248,
    "y": 1.358253,
    "theta": 5.477861
  },
  {
    "x": 1.886306,
    "y": 0.899607,
    "theta": 2.650873
  },
  {
    "x": -0.685781,
    "y": -0.610658,
    "theta": 0.282545
  },
  {
    "x": -0.458577,
    "y": 1.917321,
    "theta": 2.335621
  },
  {
    "x": -2.40025,
    "y": 1.438167,
    "theta": 5.743304
  },
  {
    "x": -0.627495,
    "y": -1.858584,
    "theta": 5.392936
  },
  {
    "x": 2.561003,
    "y": -1.089613,
    "theta": 2.739751
  },
  {
    "x": 1.815895,
    "y": 0.767727,
    "theta": 5.792412
  },
  {
    "x": 0.925073,
    "y": 1.730744,
    "theta": 1.789133
  },
  {
    "x": 0.843142,
    "y": 0.683895,
    "theta": 2.993696
  },
  {
    "x": 0.705444,
    "y": -1.839377,
    "theta": 5.616877
  },
  {
    "x": -1.949458,
    "y": -0.293707,
    "theta": 3.861194
  },
  {
    "x": -1.759532,
    "y": -0.508182,
    "theta": 0.718568
  },
  {
    "x": 1.242275,
    "y": -1.14839,
    "theta": 2.476264
  },
  {
    "x": -1.500702,
    "y": -1.278582,
    "theta": 4.747386
  }
]